odoo/addons/l10n_br_mdfe_spec/README.rst
odoo/addons/l10n_br_mdfe_spec/__init__.py
odoo/addons/l10n_br_mdfe_spec/__manifest__.py
odoo/addons/l10n_br_mdfe_spec/i18n/l10n_br_mdfe_spec.pot
odoo/addons/l10n_br_mdfe_spec/i18n/pt_BR.po
odoo/addons/l10n_br_mdfe_spec/models/__init__.py
odoo/addons/l10n_br_mdfe_spec/models/spec_mixin.py
odoo/addons/l10n_br_mdfe_spec/models/v3_0/__init__.py
odoo/addons/l10n_br_mdfe_spec/models/v3_0/ev_pagto_oper_mdfe_v3_00.py
odoo/addons/l10n_br_mdfe_spec/models/v3_0/mdfe_modal_aereo_v3_00.py
odoo/addons/l10n_br_mdfe_spec/models/v3_0/mdfe_modal_aquaviario_v3_00.py
odoo/addons/l10n_br_mdfe_spec/models/v3_0/mdfe_modal_ferroviario_v3_00.py
odoo/addons/l10n_br_mdfe_spec/models/v3_0/mdfe_modal_rodoviario_v3_00.py
odoo/addons/l10n_br_mdfe_spec/models/v3_0/mdfe_tipos_basico_v3_00.py
odoo/addons/l10n_br_mdfe_spec/models/v3_0/tipos_geral_mdfe_v3_00.py
odoo/addons/l10n_br_mdfe_spec/readme/CONTRIBUTORS.rst
odoo/addons/l10n_br_mdfe_spec/readme/DESCRIPTION.rst
odoo/addons/l10n_br_mdfe_spec/static/description/icon.png
odoo/addons/l10n_br_mdfe_spec/static/description/index.html
odoo/addons/l10n_br_mdfe_spec/tests/__init__.py
odoo/addons/l10n_br_mdfe_spec/tests/test_mdfe_import.py
odoo14_addon_l10n_br_mdfe_spec-14.0.1.1.1.dev4.dist-info/METADATA
odoo14_addon_l10n_br_mdfe_spec-14.0.1.1.1.dev4.dist-info/WHEEL
odoo14_addon_l10n_br_mdfe_spec-14.0.1.1.1.dev4.dist-info/top_level.txt
odoo14_addon_l10n_br_mdfe_spec-14.0.1.1.1.dev4.dist-info/RECORD
